vaultseal/__init__.py
vaultseal/__main__.py
vaultseal/cli.py
vaultseal/crypto.py
vaultseal/vault.py
vaultseal-0.1.1.dist-info/METADATA
vaultseal-0.1.1.dist-info/WHEEL
vaultseal-0.1.1.dist-info/entry_points.txt
vaultseal-0.1.1.dist-info/top_level.txt
vaultseal-0.1.1.dist-info/RECORD
