Metadata-Version: 2.4
Name: vaultseal
Version: 0.1.1
Summary: Encrypted local secret storage utility with a command-line interface
Author-email: Noah <allaj0412@gmail.com>
Project-URL: Homepage, https://github.com/Nipfswd/vaultseal
Project-URL: Bug Tracker, https://github.com/Nipfswd/vaultseal/issues
Keywords: encryption,secrets,cli,vault,password manager
Classifier: Programming Language :: Python :: 3
Classifier: License :: OSI Approved :: MIT License
Classifier: Operating System :: OS Independent
Classifier: Environment :: Console
Classifier: Topic :: Security :: Cryptography
Classifier: Intended Audience :: Developers
Requires-Python: >=3.7
Requires-Dist: cryptography>=3.4
Requires-Dist: pyperclip
